colortqdm/__init__.py
colortqdm/main.py
colortqdm-0.0.1.dist-info/licenses/LICENSE
colortqdm-0.0.1.dist-info/METADATA
colortqdm-0.0.1.dist-info/WHEEL
colortqdm-0.0.1.dist-info/top_level.txt
colortqdm-0.0.1.dist-info/RECORD
