Metadata-Version: 2.4
Name: colortqdm
Version: 0.0.1
Summary: Augment the tqdm class with the ability to track progress of different categories.
Home-page: https://github.com/aielte-research/colortqdm.git
Author: Bálint Csanády
Author-email: csbalint@protonmail.ch
License: MIT
Keywords: tqdm,progressbar,color
Classifier: Programming Language :: Python :: 3
Classifier: Operating System :: OS Independent
Requires-Python: >3.6
License-File: LICENSE
Requires-Dist: tqdm==4.67.1
Dynamic: author
Dynamic: author-email
Dynamic: classifier
Dynamic: description
Dynamic: description-content-type
Dynamic: home-page
Dynamic: keywords
Dynamic: license
Dynamic: license-file
Dynamic: requires-dist
Dynamic: requires-python
Dynamic: summary
